garth_mcp_server/__init__.py
garth_mcp_server-0.0.9.dist-info/METADATA
garth_mcp_server-0.0.9.dist-info/WHEEL
garth_mcp_server-0.0.9.dist-info/entry_points.txt
garth_mcp_server-0.0.9.dist-info/licenses/LICENSE
garth_mcp_server-0.0.9.dist-info/RECORD
